ayaka/__init__.py
ayaka/box.py
ayaka/config.py
ayaka/helpers.py
ayaka/init.py
ayaka/lazy.py
ayaka/master.py
ayaka/orm.py
ayaka/patch.py
nonebot_plugin_ayaka-1.0.2.dist-info/LICENSE
nonebot_plugin_ayaka-1.0.2.dist-info/METADATA
nonebot_plugin_ayaka-1.0.2.dist-info/WHEEL
nonebot_plugin_ayaka-1.0.2.dist-info/RECORD
