Metadata-Version: 2.1
Name: nonebot-plugin-ayaka
Version: 1.0.2
Summary: 为nonebot插件开发提供状态机支持
Home-page: https://bridgel.github.io/ayaka_doc/
License: MIT
Author: Su
Author-email: wxlxy316@163.com
Requires-Python: >=3.10,<4.0
Classifier: License :: OSI Approved :: MIT License
Classifier: Programming Language :: Python :: 3
Classifier: Programming Language :: Python :: 3.10
Classifier: Programming Language :: Python :: 3.11
Requires-Dist: nonebot-adapter-onebot (>=2.1.3,<3.0.0)
Requires-Dist: nonebot2 (>=2.0.0b5,<3.0.0)
Project-URL: Repository, https://github.com/bridgeL/nonebot-plugin-ayaka
